Flask_Analytics-0.6.0.dist-info/DESCRIPTION.rst
Flask_Analytics-0.6.0.dist-info/METADATA
Flask_Analytics-0.6.0.dist-info/RECORD
Flask_Analytics-0.6.0.dist-info/WHEEL
Flask_Analytics-0.6.0.dist-info/metadata.json
Flask_Analytics-0.6.0.dist-info/top_level.txt
flask_analytics/__init__.py
flask_analytics/analytics.py
flask_analytics/providers/__init__.py
flask_analytics/providers/base.py
flask_analytics/providers/chartbeat.py
flask_analytics/providers/gauges.py
flask_analytics/providers/googleclassicanalytics.py
flask_analytics/providers/googleuniversalanalytics.py
flask_analytics/providers/gosquared.py
flask_analytics/providers/piwik.py
