Metadata-Version: 1.1
Name: Flask-Analytics
Version: 0.6.0
Summary: Analytics snippets generator extension for the Flask framework
Home-page: https://github.com/citruspi/Flask-Analytics
Author: Mihir Singh (@citruspi)
Author-email: hello@mihirsingh.com
License: UNKNOWN
Platform: any
Classifier: License :: Public Domain
Classifier: Development Status :: 5 - Production/Stable
Classifier: Environment :: Plugins
Classifier: Framework :: Flask
Classifier: Intended Audience :: Developers
Classifier: Operating System :: MacOS :: MacOS X
Classifier: Operating System :: Unix
Classifier: Programming Language :: Python :: 2.7
Classifier: Programming Language :: Python :: 3.0
Classifier: Programming Language :: Python :: 3.1
Classifier: Programming Language :: Python :: 3.2
Classifier: Programming Language :: Python :: 3.3
Classifier: Programming Language :: Python :: 3.4
Classifier: Programming Language :: Python :: 3.5
Classifier: Topic :: Internet
